{
  "id": "events",
  "title": "Events 🎙️",
  "type": "gallery",
  "items": [
    {
      "description": "Software Engineering Abroad. Lessons learned from Canada and Germany.",
      "imageURL": "https://firebasestorage.googleapis.com/v0/b/rule-of-thumb-1c13c.appspot.com/o/amlcs.png?alt=media",
      "name": "ACM Uninorte Talk, 2022"
    },
    {
      "description": "Towards an Operational Data Assimilation System: A Detailed Web-Based Framework for Weather Forecast.",
      "imageURL": "https://firebasestorage.googleapis.com/v0/b/rule-of-thumb-1c13c.appspot.com/o/master.PNG?alt=media",
      "name": "Master's Thesis dissertation, 2022"
    },
    {
      "description": "Backend course (Node.js + Docker + Postgres) for the Systems and Computers Engineering program.",
      "imageURL": "https://firebasestorage.googleapis.com/v0/b/rule-of-thumb-1c13c.appspot.com/o/dsllo-applicaciones-web-backend.png?alt=media",
      "name": "Adjunct Professor, 2021"
    },
    {
      "description": "Real-time sentiment analysis of tweets by Colombian region.",
      "imageURL": "https://firebasestorage.googleapis.com/v0/b/rule-of-thumb-1c13c.appspot.com/o/sentime.png?alt=media",
      "name": "Bachelor's Degree Thesis dissertation, 2020"
    },
    {
      "description": "Deploy to heroku with Github Actions.",
      "imageURL": "https://firebasestorage.googleapis.com/v0/b/rule-of-thumb-1c13c.appspot.com/o/deploy-to-heroku-from-github-actions.png?alt=media",
      "name": "Python Barranquilla Meetup, 2020"
    },
    {
      "description": "First place out of 8 participants in Hackathon - Backend category.",
      "imageURL": "https://firebasestorage.googleapis.com/v0/b/rule-of-thumb-1c13c.appspot.com/o/koombea-hackathon.jpg?alt=media",
      "name": "Koombea Hackathon, 2019"
    },
    {
      "description": "Talk on software engineering and best practices.",
      "imageURL": "https://firebasestorage.googleapis.com/v0/b/rule-of-thumb-1c13c.appspot.com/o/talk-software-engineering.jpeg?alt=media",
      "name": "Universidad del Norte, 2019"
    },
    {
      "description": "First place out of 7 participants in Hackathon - Android category.",
      "imageURL": "https://firebasestorage.googleapis.com/v0/b/rule-of-thumb-1c13c.appspot.com/o/lya-hackathon.jpg?alt=media",
      "name": "Lya Electronic Hackathon, 2019"
    },
    {
      "description": "Speaker of 'Systems Engineering'.",
      "imageURL": "https://firebasestorage.googleapis.com/v0/b/rule-of-thumb-1c13c.appspot.com/o/inca-innovation-fair.jpg?alt=media",
      "name": "Inca School Technology and Innovation Fair, 2019"
    },
    {
      "description": "Conducted a workshop 'Tic-tac-toe AI using DP-Method'.",
      "imageURL": "https://firebasestorage.googleapis.com/v0/b/rule-of-thumb-1c13c.appspot.com/o/ieee-week.jpg?alt=media",
      "name": "Uninorte IEEE Week, 2019"
    },
    {
      "description": "Second place out of 12 participants in Hackathon - Backend category.",
      "imageURL": "https://firebasestorage.googleapis.com/v0/b/rule-of-thumb-1c13c.appspot.com/o/ideaware-hackathon.jpg?alt=media",
      "name": "Ideaware Hackathon, 2018"
    },
    {
      "description": "First place out of 8 teams in Hackathon - Android category.",
      "imageURL": "https://firebasestorage.googleapis.com/v0/b/rule-of-thumb-1c13c.appspot.com/o/nativapps-hackathon.jpg?alt=media",
      "name": "NativApps Hackathon, 2018"
    }
  ]
}
